pyterrier_rag/__init__.py
pyterrier_rag/_datasets.py
pyterrier_rag/_measures.py
pyterrier_rag/_optional.py
pyterrier_rag/_util.py
pyterrier_rag/measures.py
pyterrier_rag/model.py
pyterrier_rag/r1_searcher.py
pyterrier_rag/search_o1.py
pyterrier_rag/search_r1.py
pyterrier_rag/backend/__init__.py
pyterrier_rag/backend/_base.py
pyterrier_rag/backend/_hf.py
pyterrier_rag/backend/_openai.py
pyterrier_rag/backend/_util.py
pyterrier_rag/backend/_vllm.py
pyterrier_rag/frameworks/__init__.py
pyterrier_rag/frameworks/ir_cot.py
pyterrier_rag/frameworks/llm_as_judge.py
pyterrier_rag/frameworks/agentic/__init__.py
pyterrier_rag/frameworks/agentic/_base.py
pyterrier_rag/frameworks/agentic/_r1searcher.py
pyterrier_rag/frameworks/agentic/_searcho1.py
pyterrier_rag/frameworks/agentic/_searchr1.py
pyterrier_rag/frameworks/kg_rag/__init__.py
pyterrier_rag/frameworks/kg_rag/kg_extractor.py
pyterrier_rag/frameworks/kg_rag/kg_reasoning.py
pyterrier_rag/frameworks/kg_rag/prompts/__init__.py
pyterrier_rag/frameworks/kg_rag/prompts/generate_kg_triples_prompt.py
pyterrier_rag/frameworks/kg_rag/prompts/hotpotqa_demos/__init__.py
pyterrier_rag/frameworks/kg_rag/prompts/hotpotqa_demos/kg_generation_hotpotqa_demonstrations.py
pyterrier_rag/frameworks/kg_rag/prompts/hotpotqa_demos/rc_construction_hotpotqa_demonstrations.py
pyterrier_rag/frameworks/kg_rag/prompts/musique_demos/__init__.py
pyterrier_rag/frameworks/kg_rag/prompts/musique_demos/kg_generation_musique_demonstrations.py
pyterrier_rag/frameworks/kg_rag/prompts/musique_demos/rc_construction_musique_demonstrations.py
pyterrier_rag/frameworks/kg_rag/prompts/wikimultihopqa_demos/__init__.py
pyterrier_rag/frameworks/kg_rag/prompts/wikimultihopqa_demos/kg_generation_2wiki_demonstrations.py
pyterrier_rag/frameworks/kg_rag/prompts/wikimultihopqa_demos/rc_construction_2wiki_demonstrations.py
pyterrier_rag/prompt/__init__.py
pyterrier_rag/prompt/_base.py
pyterrier_rag/prompt/_context_aggregation.py
pyterrier_rag/prompt/wrapper.py
pyterrier_rag-0.3.0.dist-info/licenses/LICENSE
pyterrier_rag-0.3.0.dist-info/METADATA
pyterrier_rag-0.3.0.dist-info/WHEEL
pyterrier_rag-0.3.0.dist-info/entry_points.txt
pyterrier_rag-0.3.0.dist-info/top_level.txt
pyterrier_rag-0.3.0.dist-info/RECORD
