Metadata-Version: 2.4
Name: pyterrier-rag
Version: 0.3.0
Summary: PyTerrier RAG pipelines
Author-email: Craig Macdonald <craig.macdonald@glasgow.ac.uk>
Maintainer-email: Craig Macdonald <craig.macdonald@glasgow.ac.uk>
Project-URL: Repository, https://github.com/terrierteam/pyterrier_rag
Project-URL: Bug Tracker, https://github.com/terrierteam/pyterrier_rag/issues
Classifier: Programming Language :: Python
Classifier: Operating System :: OS Independent
Classifier: Topic :: Text Processing
Classifier: Topic :: Text Processing :: Indexing
Classifier: License :: OSI Approved :: MIT License
Requires-Python: >=3.10
License-File: LICENSE
Requires-Dist: python-terrier>=0.13.0
Requires-Dist: pyterrier_alpha>=0.12.0
Requires-Dist: ir_measures>=0.4.1
Requires-Dist: regex
Requires-Dist: torch
Requires-Dist: torchvision
Requires-Dist: torchaudio
Requires-Dist: transformers>=4.44.2
Requires-Dist: accelerate
Requires-Dist: openai>=1.70.0
Requires-Dist: fschat
Requires-Dist: psutil
Requires-Dist: rouge_score
Requires-Dist: pyterrier_dr
Dynamic: license-file
